{
 "generated": "2026-07-24 17:05:24 UTC",
 "started": "2026-07-15 20:00",
 "days_running": 8.9,
 "note": "Open paper positions, ranked best to worst. Unrealized P/L is marked at the latest SCAN price (hourly), not real-time. While a market is closed the last mark is held (frozen=true); display-only, not part of the integrity chain.",
 "portfolio": {
  "deployed": 20000.0,
  "value_now": 20032.72,
  "unrealized": 32.72,
  "unrealized_pct": 0.16,
  "open_positions": 20,
  "up": 8,
  "down": 12,
  "accounts": 23,
  "initial_capital": 23000.0,
  "capital_after_closed": 23000.0,
  "realized": 0.0,
  "realized_pct": 0.0,
  "total_value": 23032.72,
  "total_pct": 0.14
 },
 "out_of_market": [
  {
   "ticker": "BNB-USD",
   "tf": "1h",
   "symbol": "BNB",
   "capital": 1000.0
  },
  {
   "ticker": "EURUSD=X",
   "tf": "1h",
   "symbol": "EUR/USD",
   "capital": 1000.0
  },
  {
   "ticker": "XRP-USD",
   "tf": "1h",
   "symbol": "XRP",
   "capital": 1000.0
  }
 ],
 "open_positions": [
  {
   "n": 1,
   "symbol": "Brent",
   "ticker": "BZ=F",
   "side": "LONG",
   "leverage": 2.0,
   "tf": "1h",
   "entry_price": 85.88999938964844,
   "mark": 95.97000122070312,
   "mark_when": "2026-07-24 16:54",
   "frozen": false,
   "jump": null,
   "upl_pct": 23.47,
   "capital": 1000.0,
   "equity_now": 1234.72,
   "opened": "2026-07-15 20:04"
  },
  {
   "n": 2,
   "symbol": "Crude WTI",
   "ticker": "CL=F",
   "side": "LONG",
   "leverage": 2.0,
   "tf": "1h",
   "entry_price": 80.37999725341797,
   "mark": 88.36000061035156,
   "mark_when": "2026-07-24 16:55",
   "frozen": false,
   "jump": null,
   "upl_pct": 19.86,
   "capital": 1000.0,
   "equity_now": 1198.56,
   "opened": "2026-07-15 20:04"
  },
  {
   "n": 3,
   "symbol": "Monero",
   "ticker": "XMR-USD",
   "side": "LONG",
   "leverage": 2.0,
   "tf": "1h",
   "entry_price": 331.8248291015625,
   "mark": 353.7480163574219,
   "mark_when": "2026-07-24 13:52",
   "frozen": false,
   "jump": null,
   "upl_pct": 13.21,
   "capital": 1000.0,
   "equity_now": 1132.14,
   "opened": "2026-07-15 20:12"
  },
  {
   "n": 4,
   "symbol": "Litecoin",
   "ticker": "LTC-USD",
   "side": "LONG",
   "leverage": 2.0,
   "tf": "1h",
   "entry_price": 45.0099983215332,
   "mark": 46.150001525878906,
   "mark_when": "2026-07-24 13:54",
   "frozen": false,
   "jump": null,
   "upl_pct": 5.07,
   "capital": 1000.0,
   "equity_now": 1050.66,
   "opened": "2026-07-15 20:15"
  },
  {
   "n": 5,
   "symbol": "Silver",
   "ticker": "SI=F",
   "side": "LONG",
   "leverage": 2.0,
   "tf": "1h",
   "entry_price": 58.11000061035156,
   "mark": 58.89500045776367,
   "mark_when": "2026-07-24 16:54",
   "frozen": false,
   "jump": null,
   "upl_pct": 2.7,
   "capital": 1000.0,
   "equity_now": 1027.02,
   "opened": "2026-07-15 20:04"
  },
  {
   "n": 6,
   "symbol": "USD/JPY",
   "ticker": "USDJPY=X",
   "side": "LONG",
   "leverage": 2.0,
   "tf": "1h",
   "entry_price": 162.218994140625,
   "mark": 163.78900146484375,
   "mark_when": "2026-07-24 17:05",
   "frozen": false,
   "jump": null,
   "upl_pct": 1.94,
   "capital": 1000.0,
   "equity_now": 1019.36,
   "opened": "2026-07-15 20:15"
  },
  {
   "n": 7,
   "symbol": "USD/CAD",
   "ticker": "USDCAD=X",
   "side": "LONG",
   "leverage": 2.0,
   "tf": "1h",
   "entry_price": 1.4044100046157837,
   "mark": 1.4087799787521362,
   "mark_when": "2026-07-24 17:05",
   "frozen": false,
   "jump": null,
   "upl_pct": 0.62,
   "capital": 1000.0,
   "equity_now": 1006.22,
   "opened": "2026-07-15 20:15"
  },
  {
   "n": 8,
   "symbol": "Gold",
   "ticker": "GC=F",
   "side": "LONG",
   "leverage": 2.0,
   "tf": "1h",
   "entry_price": 4065.10009765625,
   "mark": 4068.10009765625,
   "mark_when": "2026-07-24 16:54",
   "frozen": false,
   "jump": null,
   "upl_pct": 0.15,
   "capital": 1000.0,
   "equity_now": 1001.48,
   "opened": "2026-07-15 20:04"
  },
  {
   "n": 9,
   "symbol": "AUD/USD",
   "ticker": "AUDUSD=X",
   "side": "LONG",
   "leverage": 2.0,
   "tf": "1h",
   "entry_price": 0.7008199691772461,
   "mark": 0.6993007063865662,
   "mark_when": "2026-07-24 17:04",
   "frozen": false,
   "jump": null,
   "upl_pct": -0.43,
   "capital": 1000.0,
   "equity_now": 995.66,
   "opened": "2026-07-15 20:15"
  },
  {
   "n": 10,
   "symbol": "Copper",
   "ticker": "HG=F",
   "side": "LONG",
   "leverage": 2.0,
   "tf": "1h",
   "entry_price": 6.389500141143799,
   "mark": 6.35699987411499,
   "mark_when": "2026-07-24 16:55",
   "frozen": false,
   "jump": null,
   "upl_pct": -1.02,
   "capital": 1000.0,
   "equity_now": 989.83,
   "opened": "2026-07-15 20:04"
  },
  {
   "n": 11,
   "symbol": "NatGas",
   "ticker": "NG=F",
   "side": "LONG",
   "leverage": 2.0,
   "tf": "1h",
   "entry_price": 2.9260001182556152,
   "mark": 2.9089999198913574,
   "mark_when": "2026-07-24 16:55",
   "frozen": false,
   "jump": null,
   "upl_pct": -1.16,
   "capital": 1000.0,
   "equity_now": 988.38,
   "opened": "2026-07-15 20:04"
  },
  {
   "n": 12,
   "symbol": "Dow",
   "ticker": "^DJI",
   "side": "LONG",
   "leverage": 2.0,
   "tf": "1h",
   "entry_price": 52658.640625,
   "mark": 51974.51171875,
   "mark_when": "2026-07-24 17:05",
   "frozen": false,
   "jump": null,
   "upl_pct": -2.6,
   "capital": 1000.0,
   "equity_now": 974.02,
   "opened": "2026-07-15 20:00"
  },
  {
   "n": 13,
   "symbol": "Bitcoin",
   "ticker": "BTC-USD",
   "side": "LONG",
   "leverage": 2.0,
   "tf": "1h",
   "entry_price": 64904.3984375,
   "mark": 63925.96875,
   "mark_when": "2026-07-24 13:54",
   "frozen": false,
   "jump": null,
   "upl_pct": -3.01,
   "capital": 1000.0,
   "equity_now": 969.85,
   "opened": "2026-07-15 20:14"
  },
  {
   "n": 14,
   "symbol": "GBP/USD",
   "ticker": "GBPUSD=X",
   "side": "LONG",
   "leverage": 2.0,
   "tf": "1h",
   "entry_price": 1.3535828590393066,
   "mark": 1.3331378698349,
   "mark_when": "2026-07-24 17:04",
   "frozen": false,
   "jump": null,
   "upl_pct": -3.02,
   "capital": 1000.0,
   "equity_now": 969.79,
   "opened": "2026-07-15 20:15"
  },
  {
   "n": 15,
   "symbol": "S&P 500",
   "ticker": "^GSPC",
   "side": "LONG",
   "leverage": 2.0,
   "tf": "1h",
   "entry_price": 7572.39990234375,
   "mark": 7435.5498046875,
   "mark_when": "2026-07-24 17:05",
   "frozen": false,
   "jump": null,
   "upl_pct": -3.61,
   "capital": 1000.0,
   "equity_now": 963.86,
   "opened": "2026-07-15 20:00"
  },
  {
   "n": 16,
   "symbol": "Ethereum",
   "ticker": "ETH-USD",
   "side": "LONG",
   "leverage": 2.0,
   "tf": "1h",
   "entry_price": 1921.719970703125,
   "mark": 1848.239990234375,
   "mark_when": "2026-07-24 13:54",
   "frozen": false,
   "jump": null,
   "upl_pct": -7.65,
   "capital": 1000.0,
   "equity_now": 923.53,
   "opened": "2026-07-15 20:14"
  },
  {
   "n": 17,
   "symbol": "Nasdaq 100",
   "ticker": "^NDX",
   "side": "LONG",
   "leverage": 2.0,
   "tf": "1h",
   "entry_price": 29502.595703125,
   "mark": 28317.3515625,
   "mark_when": "2026-07-24 17:05",
   "frozen": false,
   "jump": null,
   "upl_pct": -8.03,
   "capital": 1000.0,
   "equity_now": 919.65,
   "opened": "2026-07-15 20:00"
  },
  {
   "n": 18,
   "symbol": "Solana",
   "ticker": "SOL-USD",
   "side": "LONG",
   "leverage": 2.0,
   "tf": "1h",
   "entry_price": 77.16000366210938,
   "mark": 73.98999786376953,
   "mark_when": "2026-07-24 13:54",
   "frozen": false,
   "jump": null,
   "upl_pct": -8.22,
   "capital": 1000.0,
   "equity_now": 917.83,
   "opened": "2026-07-15 20:14"
  },
  {
   "n": 19,
   "symbol": "Platinum",
   "ticker": "PL=F",
   "side": "LONG",
   "leverage": 2.0,
   "tf": "1h",
   "entry_price": 1691.0999755859375,
   "mark": 1604.699951171875,
   "mark_when": "2026-07-24 16:54",
   "frozen": false,
   "jump": null,
   "upl_pct": -10.22,
   "capital": 1000.0,
   "equity_now": 897.82,
   "opened": "2026-07-15 20:04"
  },
  {
   "n": 20,
   "symbol": "Dogecoin",
   "ticker": "DOGE-USD",
   "side": "LONG",
   "leverage": 2.0,
   "tf": "1h",
   "entry_price": 0.07382000237703323,
   "mark": 0.06836999952793121,
   "mark_when": "2026-07-24 13:54",
   "frozen": false,
   "jump": null,
   "upl_pct": -14.77,
   "capital": 1000.0,
   "equity_now": 852.34,
   "opened": "2026-07-15 20:14"
  }
 ]
}